privacy_api/__init__.py
privacy_api/client.py
privacy_api/models.py
privacy_api/schemas.py
privacy_api-0.1.10.dist-info/LICENSE
privacy_api-0.1.10.dist-info/METADATA
privacy_api-0.1.10.dist-info/WHEEL
privacy_api-0.1.10.dist-info/top_level.txt
privacy_api-0.1.10.dist-info/RECORD
